wenxin_api/__init__.py
wenxin_api/args.py
wenxin_api/base_object.py
wenxin_api/const.py
wenxin_api/error.py
wenxin_api/log.py
wenxin_api/requestor.py
wenxin_api/variable.py
wenxin_api/version.txt
wenxin_api/api/__init__.py
wenxin_api/api/base_api.py
wenxin_api/api/dataset_api.py
wenxin_api/api/model_api.py
wenxin_api/api/task_api.py
wenxin_api/api/train_api.py
wenxin_api/tasks/__init__.py
wenxin_api/tasks/cloze.py
wenxin_api/tasks/composition.py
wenxin_api/tasks/couplet.py
wenxin_api/tasks/free_qa.py
wenxin_api/tasks/novel.py
wenxin_api/tasks/official_documents.py
wenxin_api/tasks/paraphrase.py
wenxin_api/tasks/qa_extract.py
wenxin_api/tasks/query_generation.py
wenxin_api/tasks/summarization.py
wenxin_api/tasks/text_generation.py
wenxin_api/tasks/text_to_image.py
wenxin_api/tasks/text_to_image_training.py
wenxin_api-0.2.1.dist-info/LICENSE
wenxin_api-0.2.1.dist-info/METADATA
wenxin_api-0.2.1.dist-info/WHEEL
wenxin_api-0.2.1.dist-info/top_level.txt
wenxin_api-0.2.1.dist-info/RECORD
