Metadata-Version: 2.1
Name: wenxin-api
Version: 0.2.1
Summary: wenxin api client for ernie 1p5b, 10b and 100b prompt-tuning and serving
Home-page: UNKNOWN
Author: xuchenning
Author-email: UNKNOWN
License: UNKNOWN
Platform: UNKNOWN
Requires-Dist: requests (>=2.20)
Requires-Dist: tqdm
